ghostcord/ghostcord___init__.py
ghostcord/ghostcord_client.py
ghostcord/ghostcord_commands.py
ghostcord/ghostcord_errors.py
ghostcord/ghostcord_events.py
ghostcord/ghostcord_models.py
ghostcord/ghostcord_presence.py
ghostcord/ghostcord_ratelimit.py
ghostcord/ghostcord_utils.py
ghostcord-0.2.0.dist-info/licenses/LICENSE
ghostcord-0.2.0.dist-info/METADATA
ghostcord-0.2.0.dist-info/WHEEL
ghostcord-0.2.0.dist-info/top_level.txt
ghostcord-0.2.0.dist-info/RECORD
