Metadata-Version: 2.4
Name: ghostcord
Version: 0.2.0
Summary: A lightweight, async Python library for controlling Discord user accounts (selfbot behavior).
Author-email: xAI <support@x.ai>
License: MIT License
Project-URL: Homepage, https://github.com/xAI/GhostCord
Project-URL: Repository, https://github.com/xAI/GhostCord
Project-URL: Issues, https://github.com/xAI/GhostCord/issues
Requires-Python: >=3.8
License-File: LICENSE
Requires-Dist: httpx>=0.24.0
Requires-Dist: websockets>=11.0
Dynamic: license-file
